snipsskillscore/__init__.py
snipsskillscore/audio_player.py
snipsskillscore/instant_time.py
snipsskillscore/intent_parser.py
snipsskillscore/leds_service.py
snipsskillscore/pretty_printer.py
snipsskillscore/server.py
snipsskillscore/singleton.py
snipsskillscore/sound_service.py
snipsskillscore/state_handler.py
snipsskillscore/thread_handler.py
snipsskillscore/time_interval.py
snipsskillscore/tts.py
snipsskillscore/usb_utils.py
snipsskillscore/data/sounds/music_marimba_error_chord_2x.wav
snipsskillscore/data/sounds/pad_glow_power_off.wav
snipsskillscore/data/sounds/pad_glow_welcome1.wav
snipsskillscore/data/sounds/pad_soft_off.wav
snipsskillscore/data/sounds/pad_soft_on.wav
snipsskillscore-0.1.5.9.5.dist-info/DESCRIPTION.rst
snipsskillscore-0.1.5.9.5.dist-info/METADATA
snipsskillscore-0.1.5.9.5.dist-info/RECORD
snipsskillscore-0.1.5.9.5.dist-info/WHEEL
snipsskillscore-0.1.5.9.5.dist-info/metadata.json
snipsskillscore-0.1.5.9.5.dist-info/top_level.txt
